itlmon/__init__.py
itlmon/__main__.py
itlmon/chat_interface.py
itlmon/cluster_interface.py
itlmon/command_parser.py
itlmon/directory_watcher.py
itlmon/s3_file_downloader.py
itlmon/stream_interface.py
itlmon-0.0.3.dist-info/METADATA
itlmon-0.0.3.dist-info/WHEEL
itlmon-0.0.3.dist-info/licenses/LICENSE
itlmon-0.0.3.dist-info/RECORD
